pytempl_icons/__init__.py
pytempl_icons/_base.py
pytempl_icons/abstract.py
pytempl_icons/arrows.py
pytempl_icons/objects.py
pytempl_icons-0.2.2.dist-info/METADATA
pytempl_icons-0.2.2.dist-info/WHEEL
pytempl_icons-0.2.2.dist-info/RECORD
